LICENSE
MANIFEST.in
README.rst
requirements.txt
setup.cfg
setup.py
ckanext/__init__.py
ckanext/onesaitplatform/__init__.py
ckanext/onesaitplatform/controller.py
ckanext/onesaitplatform/plugin.py
ckanext/onesaitplatform/public/animate.css
ckanext/onesaitplatform/public/fonts.css
ckanext/onesaitplatform/public/onesait.css
ckanext/onesaitplatform/public/fonts/FontAwesome.otf
ckanext/onesaitplatform/public/fonts/Linearicons.ttf
ckanext/onesaitplatform/public/fonts/Linearicons.woff
ckanext/onesaitplatform/public/fonts/MaterialIcons-Regular.ttf
ckanext/onesaitplatform/public/fonts/MaterialIcons-Regular.woff
ckanext/onesaitplatform/public/fonts/MaterialIcons-Regular.woff2
ckanext/onesaitplatform/public/fonts/MyriadPro-Regular.ttf
ckanext/onesaitplatform/public/fonts/MyriadPro-Regular.woff
ckanext/onesaitplatform/public/fonts/PlayfairDisplay-Regular.ttf
ckanext/onesaitplatform/public/fonts/PlayfairDisplay-Regular.woff
ckanext/onesaitplatform/public/fonts/SohoGothicPro-Light.otf
ckanext/onesaitplatform/public/fonts/SohoGothicPro-Light.ttf
ckanext/onesaitplatform/public/fonts/SohoGothicPro-Light.woff
ckanext/onesaitplatform/public/fonts/SohoGothicPro-Medium.otf
ckanext/onesaitplatform/public/fonts/SohoGothicPro-Medium.ttf
ckanext/onesaitplatform/public/fonts/SohoGothicPro-Medium.woff
ckanext/onesaitplatform/public/fonts/SohoGothicW04-Regular.ttf
ckanext/onesaitplatform/public/fonts/SohoGothicW04-Regular.woff
ckanext/onesaitplatform/public/fonts/fl-bigmug-line.ttf
ckanext/onesaitplatform/public/fonts/fl-bigmug-line.woff
ckanext/onesaitplatform/public/fonts/fontawesome-webfont.ttf
ckanext/onesaitplatform/public/fonts/fontawesome-webfont.woff
ckanext/onesaitplatform/public/fonts/fontawesome-webfont.woff2
ckanext/onesaitplatform/public/fonts/icomoon.ttf
ckanext/onesaitplatform/public/fonts/icomoon.woff
ckanext/onesaitplatform/public/fonts/lg.ttf
ckanext/onesaitplatform/public/fonts/lg.woff
ckanext/onesaitplatform/public/fonts/materialdesignicons-webfont.ttf
ckanext_onesaitplatform.egg-info/PKG-INFO
ckanext_onesaitplatform.egg-info/SOURCES.txt
ckanext_onesaitplatform.egg-info/dependency_links.txt
ckanext_onesaitplatform.egg-info/entry_points.txt
ckanext_onesaitplatform.egg-info/namespace_packages.txt
ckanext_onesaitplatform.egg-info/top_level.txt