Metadata-Version: 2.1
Name: ckanext-onesaitplatform
Version: 1.0.1
Summary: onesaitplatform customization portal
Home-page: https://github.com/onesaitplatform/ckanext-onesaitplatform
Author: onesaitplatform
Author-email: onesaitplatform@onesaitplatform.com
License: AGPL
Keywords: CKAN onesaitplatform
Platform: UNKNOWN
Classifier: Development Status :: 4 - Beta
Classifier: License :: OSI Approved :: GNU Affero General Public License v3 or later (AGPLv3+)
Classifier: Programming Language :: Python :: 2.7
